vyper_cli.py
flake8_vyper-0.1.10.dist-info/METADATA
flake8_vyper-0.1.10.dist-info/WHEEL
flake8_vyper-0.1.10.dist-info/entry_points.txt
flake8_vyper-0.1.10.dist-info/top_level.txt
flake8_vyper-0.1.10.dist-info/RECORD
