Metadata-Version: 2.1
Name: flake8-vyper
Version: 0.1.10
Summary: Plugin for flake8 to support Vyper
Home-page: https://gitlab.com/mikeshultz/flake8-vyper
Author: Mike Shultz
Author-email: mike@mikeshultz.com
License: MIT
Platform: UNKNOWN
Classifier: Framework :: Flake8
Classifier: Environment :: Console
Classifier: Intended Audience :: Developers
Classifier: License :: OSI Approved :: MIT License
Classifier: Programming Language :: Python
Classifier: Programming Language :: Python :: 2
Classifier: Programming Language :: Python :: 3
Classifier: Topic :: Software Development :: Libraries :: Python Modules
Classifier: Topic :: Software Development :: Quality Assurance
Requires-Dist: flake8 (>=3.0.0)
Requires-Dist: vyper (==0.1.0b9)
